{
  "startTime": 1754170500998,
  "rpcCalls": 0,
  "lastBlockNumber": 25077624,
  "lastUpdateTime": 1778571992853,
  "updateHistory": [
    {
      "timestamp": "2026-05-11T23:31:34.640Z",
      "block": 25075156,
      "rpcCalls": 6,
      "dataChanged": true,
      "errors": []
    },
    {
      "timestamp": "2026-05-11T23:36:33.328Z",
      "block": 25075181,
      "rpcCalls": 6,
      "dataChanged": true,
      "errors": []
    },
    {
      "timestamp": "2026-05-11T23:41:41.295Z",
      "block": 25075206,
      "rpcCalls": 6,
      "dataChanged": true,
      "errors": []
    },
    {
      "timestamp": "2026-05-11T23:46:49.686Z",
      "block": 25075231,
      "rpcCalls": 6,
      "dataChanged": true,
      "errors": []
    },
    {
      "timestamp": "2026-05-11T23:51:37.905Z",
      "block": 25075255,
      "rpcCalls": 6,
      "dataChanged": true,
      "errors": []
    },
    {
      "timestamp": "2026-05-11T23:56:52.381Z",
      "block": 25075280,
      "rpcCalls": 6,
      "dataChanged": true,
      "errors": []
    },
    {
      "timestamp": "2026-05-12T00:01:56.292Z",
      "block": 25075305,
      "rpcCalls": 6,
      "dataChanged": true,
      "errors": []
    },
    {
      "timestamp": "2026-05-12T00:06:37.723Z",
      "block": 25075330,
      "rpcCalls": 6,
      "dataChanged": true,
      "errors": []
    },
    {
      "timestamp": "2026-05-12T00:11:40.484Z",
      "block": 25075355,
      "rpcCalls": 6,
      "dataChanged": true,
      "errors": []
    },
    {
      "timestamp": "2026-05-12T00:16:42.204Z",
      "block": 25075380,
      "rpcCalls": 6,
      "dataChanged": true,
      "errors": []
    },
    {
      "timestamp": "2026-05-12T00:21:40.271Z",
      "block": 25075405,
      "rpcCalls": 6,
      "dataChanged": true,
      "errors": []
    },
    {
      "timestamp": "2026-05-12T00:26:44.165Z",
      "block": 25075430,
      "rpcCalls": 6,
      "dataChanged": true,
      "errors": []
    },
    {
      "timestamp": "2026-05-12T00:31:41.760Z",
      "block": 25075455,
      "rpcCalls": 6,
      "dataChanged": true,
      "errors": []
    },
    {
      "timestamp": "2026-05-12T00:36:34.965Z",
      "block": 25075480,
      "rpcCalls": 6,
      "dataChanged": true,
      "errors": []
    },
    {
      "timestamp": "2026-05-12T00:41:34.044Z",
      "block": 25075505,
      "rpcCalls": 6,
      "dataChanged": true,
      "errors": []
    },
    {
      "timestamp": "2026-05-12T00:46:39.319Z",
      "block": 25075530,
      "rpcCalls": 6,
      "dataChanged": true,
      "errors": []
    },
    {
      "timestamp": "2026-05-12T00:51:38.946Z",
      "block": 25075555,
      "rpcCalls": 6,
      "dataChanged": true,
      "errors": []
    },
    {
      "timestamp": "2026-05-12T00:56:44.147Z",
      "block": 25075580,
      "rpcCalls": 6,
      "dataChanged": true,
      "errors": []
    },
    {
      "timestamp": "2026-05-12T01:01:39.601Z",
      "block": 25075605,
      "rpcCalls": 6,
      "dataChanged": true,
      "errors": []
    },
    {
      "timestamp": "2026-05-12T01:06:37.055Z",
      "block": 25075630,
      "rpcCalls": 6,
      "dataChanged": true,
      "errors": []
    },
    {
      "timestamp": "2026-05-12T01:11:35.609Z",
      "block": 25075655,
      "rpcCalls": 6,
      "dataChanged": true,
      "errors": []
    },
    {
      "timestamp": "2026-05-12T01:16:37.172Z",
      "block": 25075680,
      "rpcCalls": 6,
      "dataChanged": true,
      "errors": []
    },
    {
      "timestamp": "2026-05-12T01:21:33.958Z",
      "block": 25075704,
      "rpcCalls": 6,
      "dataChanged": true,
      "errors": []
    },
    {
      "timestamp": "2026-05-12T01:26:44.396Z",
      "block": 25075729,
      "rpcCalls": 6,
      "dataChanged": true,
      "errors": []
    },
    {
      "timestamp": "2026-05-12T01:31:32.248Z",
      "block": 25075754,
      "rpcCalls": 6,
      "dataChanged": true,
      "errors": []
    },
    {
      "timestamp": "2026-05-12T01:36:37.900Z",
      "block": 25075778,
      "rpcCalls": 6,
      "dataChanged": true,
      "errors": []
    },
    {
      "timestamp": "2026-05-12T01:41:32.786Z",
      "block": 25075803,
      "rpcCalls": 6,
      "dataChanged": true,
      "errors": []
    },
    {
      "timestamp": "2026-05-12T01:46:37.852Z",
      "block": 25075828,
      "rpcCalls": 6,
      "dataChanged": true,
      "errors": []
    },
    {
      "timestamp": "2026-05-12T01:51:38.340Z",
      "block": 25075853,
      "rpcCalls": 6,
      "dataChanged": true,
      "errors": []
    },
    {
      "timestamp": "2026-05-12T01:56:33.269Z",
      "block": 25075878,
      "rpcCalls": 6,
      "dataChanged": true,
      "errors": []
    },
    {
      "timestamp": "2026-05-12T02:01:34.522Z",
      "block": 25075903,
      "rpcCalls": 6,
      "dataChanged": true,
      "errors": []
    },
    {
      "timestamp": "2026-05-12T02:06:33.310Z",
      "block": 25075928,
      "rpcCalls": 6,
      "dataChanged": true,
      "errors": []
    },
    {
      "timestamp": "2026-05-12T02:11:34.520Z",
      "block": 25075953,
      "rpcCalls": 6,
      "dataChanged": true,
      "errors": []
    },
    {
      "timestamp": "2026-05-12T02:16:37.144Z",
      "block": 25075978,
      "rpcCalls": 6,
      "dataChanged": true,
      "errors": []
    },
    {
      "timestamp": "2026-05-12T02:21:33.967Z",
      "block": 25076003,
      "rpcCalls": 6,
      "dataChanged": true,
      "errors": []
    },
    {
      "timestamp": "2026-05-12T02:26:37.725Z",
      "block": 25076028,
      "rpcCalls": 6,
      "dataChanged": true,
      "errors": []
    },
    {
      "timestamp": "2026-05-12T02:31:37.504Z",
      "block": 25076053,
      "rpcCalls": 6,
      "dataChanged": true,
      "errors": []
    },
    {
      "timestamp": "2026-05-12T02:36:30.737Z",
      "block": 25076078,
      "rpcCalls": 6,
      "dataChanged": true,
      "errors": []
    },
    {
      "timestamp": "2026-05-12T02:41:32.094Z",
      "block": 25076102,
      "rpcCalls": 6,
      "dataChanged": true,
      "errors": []
    },
    {
      "timestamp": "2026-05-12T02:46:50.098Z",
      "block": 25076127,
      "rpcCalls": 6,
      "dataChanged": true,
      "errors": []
    },
    {
      "timestamp": "2026-05-12T02:51:45.936Z",
      "block": 25076152,
      "rpcCalls": 6,
      "dataChanged": true,
      "errors": []
    },
    {
      "timestamp": "2026-05-12T02:56:31.375Z",
      "block": 25076177,
      "rpcCalls": 6,
      "dataChanged": true,
      "errors": []
    },
    {
      "timestamp": "2026-05-12T03:01:34.188Z",
      "block": 25076202,
      "rpcCalls": 6,
      "dataChanged": true,
      "errors": []
    },
    {
      "timestamp": "2026-05-12T03:06:35.960Z",
      "block": 25076227,
      "rpcCalls": 6,
      "dataChanged": true,
      "errors": []
    },
    {
      "timestamp": "2026-05-12T03:11:35.961Z",
      "block": 25076252,
      "rpcCalls": 6,
      "dataChanged": true,
      "errors": []
    },
    {
      "timestamp": "2026-05-12T03:16:33.915Z",
      "block": 25076277,
      "rpcCalls": 6,
      "dataChanged": true,
      "errors": []
    },
    {
      "timestamp": "2026-05-12T03:21:31.925Z",
      "block": 25076302,
      "rpcCalls": 6,
      "dataChanged": true,
      "errors": []
    },
    {
      "timestamp": "2026-05-12T03:26:32.695Z",
      "block": 25076327,
      "rpcCalls": 6,
      "dataChanged": true,
      "errors": []
    },
    {
      "timestamp": "2026-05-12T03:31:33.028Z",
      "block": 25076352,
      "rpcCalls": 6,
      "dataChanged": true,
      "errors": []
    },
    {
      "timestamp": "2026-05-12T03:36:32.758Z",
      "block": 25076377,
      "rpcCalls": 6,
      "dataChanged": true,
      "errors": []
    },
    {
      "timestamp": "2026-05-12T03:41:33.652Z",
      "block": 25076402,
      "rpcCalls": 6,
      "dataChanged": true,
      "errors": []
    },
    {
      "timestamp": "2026-05-12T03:46:35.605Z",
      "block": 25076427,
      "rpcCalls": 6,
      "dataChanged": true,
      "errors": []
    },
    {
      "timestamp": "2026-05-12T03:51:37.449Z",
      "block": 25076452,
      "rpcCalls": 6,
      "dataChanged": true,
      "errors": []
    },
    {
      "timestamp": "2026-05-12T03:56:32.880Z",
      "block": 25076477,
      "rpcCalls": 6,
      "dataChanged": true,
      "errors": []
    },
    {
      "timestamp": "2026-05-12T04:01:36.085Z",
      "block": 25076502,
      "rpcCalls": 6,
      "dataChanged": true,
      "errors": []
    },
    {
      "timestamp": "2026-05-12T04:06:33.158Z",
      "block": 25076527,
      "rpcCalls": 6,
      "dataChanged": true,
      "errors": []
    },
    {
      "timestamp": "2026-05-12T04:11:34.480Z",
      "block": 25076552,
      "rpcCalls": 6,
      "dataChanged": true,
      "errors": []
    },
    {
      "timestamp": "2026-05-12T04:16:34.212Z",
      "block": 25076577,
      "rpcCalls": 6,
      "dataChanged": true,
      "errors": []
    },
    {
      "timestamp": "2026-05-12T04:21:28.720Z",
      "block": 25076600,
      "rpcCalls": 6,
      "dataChanged": true,
      "errors": []
    },
    {
      "timestamp": "2026-05-12T04:26:35.749Z",
      "block": 25076625,
      "rpcCalls": 6,
      "dataChanged": true,
      "errors": []
    },
    {
      "timestamp": "2026-05-12T04:31:37.642Z",
      "block": 25076650,
      "rpcCalls": 6,
      "dataChanged": true,
      "errors": []
    },
    {
      "timestamp": "2026-05-12T04:36:31.847Z",
      "block": 25076675,
      "rpcCalls": 6,
      "dataChanged": true,
      "errors": []
    },
    {
      "timestamp": "2026-05-12T04:41:30.288Z",
      "block": 25076700,
      "rpcCalls": 6,
      "dataChanged": true,
      "errors": []
    },
    {
      "timestamp": "2026-05-12T04:46:32.959Z",
      "block": 25076725,
      "rpcCalls": 6,
      "dataChanged": true,
      "errors": []
    },
    {
      "timestamp": "2026-05-12T04:51:34.173Z",
      "block": 25076750,
      "rpcCalls": 6,
      "dataChanged": true,
      "errors": []
    },
    {
      "timestamp": "2026-05-12T04:56:40.384Z",
      "block": 25076775,
      "rpcCalls": 6,
      "dataChanged": true,
      "errors": []
    },
    {
      "timestamp": "2026-05-12T05:01:34.217Z",
      "block": 25076800,
      "rpcCalls": 6,
      "dataChanged": true,
      "errors": []
    },
    {
      "timestamp": "2026-05-12T05:06:36.957Z",
      "block": 25076825,
      "rpcCalls": 6,
      "dataChanged": true,
      "errors": []
    },
    {
      "timestamp": "2026-05-12T05:11:40.910Z",
      "block": 25076850,
      "rpcCalls": 6,
      "dataChanged": true,
      "errors": []
    },
    {
      "timestamp": "2026-05-12T05:16:33.748Z",
      "block": 25076875,
      "rpcCalls": 6,
      "dataChanged": true,
      "errors": []
    },
    {
      "timestamp": "2026-05-12T05:21:30.274Z",
      "block": 25076900,
      "rpcCalls": 6,
      "dataChanged": true,
      "errors": []
    },
    {
      "timestamp": "2026-05-12T05:26:32.206Z",
      "block": 25076925,
      "rpcCalls": 6,
      "dataChanged": true,
      "errors": []
    },
    {
      "timestamp": "2026-05-12T05:31:31.436Z",
      "block": 25076950,
      "rpcCalls": 6,
      "dataChanged": true,
      "errors": []
    },
    {
      "timestamp": "2026-05-12T05:36:33.330Z",
      "block": 25076975,
      "rpcCalls": 6,
      "dataChanged": true,
      "errors": []
    },
    {
      "timestamp": "2026-05-12T05:41:32.978Z",
      "block": 25077000,
      "rpcCalls": 6,
      "dataChanged": true,
      "errors": []
    },
    {
      "timestamp": "2026-05-12T05:46:32.623Z",
      "block": 25077025,
      "rpcCalls": 6,
      "dataChanged": true,
      "errors": []
    },
    {
      "timestamp": "2026-05-12T05:51:30.038Z",
      "block": 25077050,
      "rpcCalls": 6,
      "dataChanged": true,
      "errors": []
    },
    {
      "timestamp": "2026-05-12T05:56:34.457Z",
      "block": 25077075,
      "rpcCalls": 6,
      "dataChanged": true,
      "errors": []
    },
    {
      "timestamp": "2026-05-12T06:01:33.278Z",
      "block": 25077100,
      "rpcCalls": 6,
      "dataChanged": true,
      "errors": []
    },
    {
      "timestamp": "2026-05-12T06:06:35.601Z",
      "block": 25077125,
      "rpcCalls": 6,
      "dataChanged": true,
      "errors": []
    },
    {
      "timestamp": "2026-05-12T06:11:31.485Z",
      "block": 25077150,
      "rpcCalls": 6,
      "dataChanged": true,
      "errors": []
    },
    {
      "timestamp": "2026-05-12T06:16:29.641Z",
      "block": 25077175,
      "rpcCalls": 6,
      "dataChanged": true,
      "errors": []
    },
    {
      "timestamp": "2026-05-12T06:21:31.780Z",
      "block": 25077200,
      "rpcCalls": 6,
      "dataChanged": true,
      "errors": []
    },
    {
      "timestamp": "2026-05-12T06:26:33.649Z",
      "block": 25077225,
      "rpcCalls": 6,
      "dataChanged": true,
      "errors": []
    },
    {
      "timestamp": "2026-05-12T06:31:31.879Z",
      "block": 25077250,
      "rpcCalls": 6,
      "dataChanged": true,
      "errors": []
    },
    {
      "timestamp": "2026-05-12T06:36:29.435Z",
      "block": 25077275,
      "rpcCalls": 6,
      "dataChanged": true,
      "errors": []
    },
    {
      "timestamp": "2026-05-12T06:41:30.470Z",
      "block": 25077300,
      "rpcCalls": 6,
      "dataChanged": true,
      "errors": []
    },
    {
      "timestamp": "2026-05-12T06:46:51.328Z",
      "block": 25077325,
      "rpcCalls": 6,
      "dataChanged": true,
      "errors": []
    },
    {
      "timestamp": "2026-05-12T06:51:31.758Z",
      "block": 25077350,
      "rpcCalls": 6,
      "dataChanged": true,
      "errors": []
    },
    {
      "timestamp": "2026-05-12T06:56:33.127Z",
      "block": 25077375,
      "rpcCalls": 6,
      "dataChanged": true,
      "errors": []
    },
    {
      "timestamp": "2026-05-12T07:01:32.918Z",
      "block": 25077400,
      "rpcCalls": 6,
      "dataChanged": true,
      "errors": []
    },
    {
      "timestamp": "2026-05-12T07:06:34.225Z",
      "block": 25077424,
      "rpcCalls": 6,
      "dataChanged": true,
      "errors": []
    },
    {
      "timestamp": "2026-05-12T07:11:32.823Z",
      "block": 25077449,
      "rpcCalls": 6,
      "dataChanged": true,
      "errors": []
    },
    {
      "timestamp": "2026-05-12T07:16:29.347Z",
      "block": 25077474,
      "rpcCalls": 6,
      "dataChanged": true,
      "errors": []
    },
    {
      "timestamp": "2026-05-12T07:21:33.788Z",
      "block": 25077499,
      "rpcCalls": 6,
      "dataChanged": true,
      "errors": []
    },
    {
      "timestamp": "2026-05-12T07:26:34.988Z",
      "block": 25077524,
      "rpcCalls": 6,
      "dataChanged": true,
      "errors": []
    },
    {
      "timestamp": "2026-05-12T07:31:32.894Z",
      "block": 25077549,
      "rpcCalls": 6,
      "dataChanged": true,
      "errors": []
    },
    {
      "timestamp": "2026-05-12T07:36:32.385Z",
      "block": 25077574,
      "rpcCalls": 6,
      "dataChanged": true,
      "errors": []
    },
    {
      "timestamp": "2026-05-12T07:41:30.513Z",
      "block": 25077599,
      "rpcCalls": 6,
      "dataChanged": true,
      "errors": []
    },
    {
      "timestamp": "2026-05-12T07:46:32.853Z",
      "block": 25077624,
      "rpcCalls": 6,
      "dataChanged": true,
      "errors": []
    }
  ],
  "totalRpcCalls": 367532
}