{
  "startTime": 1754170500998,
  "rpcCalls": 0,
  "lastBlockNumber": 24194865,
  "lastUpdateTime": 1767934556409,
  "updateHistory": [
    {
      "timestamp": "2026-01-08T21:37:01.771Z",
      "block": 24192682,
      "rpcCalls": 6,
      "dataChanged": true,
      "errors": []
    },
    {
      "timestamp": "2026-01-08T21:40:48.143Z",
      "block": 24192701,
      "rpcCalls": 6,
      "dataChanged": true,
      "errors": []
    },
    {
      "timestamp": "2026-01-08T21:45:45.628Z",
      "block": 24192726,
      "rpcCalls": 6,
      "dataChanged": true,
      "errors": []
    },
    {
      "timestamp": "2026-01-08T21:50:45.207Z",
      "block": 24192751,
      "rpcCalls": 6,
      "dataChanged": true,
      "errors": []
    },
    {
      "timestamp": "2026-01-08T21:55:53.401Z",
      "block": 24192777,
      "rpcCalls": 7,
      "dataChanged": true,
      "errors": []
    },
    {
      "timestamp": "2026-01-08T22:00:47.016Z",
      "block": 24192802,
      "rpcCalls": 6,
      "dataChanged": true,
      "errors": []
    },
    {
      "timestamp": "2026-01-08T22:04:39.406Z",
      "block": 24192821,
      "rpcCalls": 6,
      "dataChanged": true,
      "errors": []
    },
    {
      "timestamp": "2026-01-08T22:05:45.313Z",
      "block": 24192826,
      "rpcCalls": 6,
      "dataChanged": true,
      "errors": []
    },
    {
      "timestamp": "2026-01-08T22:10:46.399Z",
      "block": 24192851,
      "rpcCalls": 6,
      "dataChanged": true,
      "errors": []
    },
    {
      "timestamp": "2026-01-08T22:15:46.329Z",
      "block": 24192876,
      "rpcCalls": 6,
      "dataChanged": true,
      "errors": []
    },
    {
      "timestamp": "2026-01-08T22:20:50.607Z",
      "block": 24192901,
      "rpcCalls": 6,
      "dataChanged": true,
      "errors": []
    },
    {
      "timestamp": "2026-01-08T22:25:45.710Z",
      "block": 24192926,
      "rpcCalls": 6,
      "dataChanged": true,
      "errors": []
    },
    {
      "timestamp": "2026-01-08T22:30:46.040Z",
      "block": 24192951,
      "rpcCalls": 6,
      "dataChanged": true,
      "errors": []
    },
    {
      "timestamp": "2026-01-08T22:32:25.511Z",
      "block": 24192959,
      "rpcCalls": 6,
      "dataChanged": true,
      "errors": []
    },
    {
      "timestamp": "2026-01-08T22:35:46.403Z",
      "block": 24192976,
      "rpcCalls": 6,
      "dataChanged": true,
      "errors": []
    },
    {
      "timestamp": "2026-01-08T22:40:50.401Z",
      "block": 24193002,
      "rpcCalls": 6,
      "dataChanged": true,
      "errors": []
    },
    {
      "timestamp": "2026-01-08T22:45:48.442Z",
      "block": 24193027,
      "rpcCalls": 6,
      "dataChanged": true,
      "errors": []
    },
    {
      "timestamp": "2026-01-08T22:50:50.244Z",
      "block": 24193051,
      "rpcCalls": 6,
      "dataChanged": true,
      "errors": []
    },
    {
      "timestamp": "2026-01-08T22:55:49.416Z",
      "block": 24193075,
      "rpcCalls": 6,
      "dataChanged": true,
      "errors": []
    },
    {
      "timestamp": "2026-01-08T23:00:48.196Z",
      "block": 24193099,
      "rpcCalls": 6,
      "dataChanged": true,
      "errors": []
    },
    {
      "timestamp": "2026-01-08T23:05:45.705Z",
      "block": 24193124,
      "rpcCalls": 6,
      "dataChanged": true,
      "errors": []
    },
    {
      "timestamp": "2026-01-08T23:10:46.847Z",
      "block": 24193149,
      "rpcCalls": 6,
      "dataChanged": true,
      "errors": []
    },
    {
      "timestamp": "2026-01-08T23:15:45.897Z",
      "block": 24193173,
      "rpcCalls": 6,
      "dataChanged": true,
      "errors": []
    },
    {
      "timestamp": "2026-01-08T23:20:54.524Z",
      "block": 24193198,
      "rpcCalls": 6,
      "dataChanged": true,
      "errors": []
    },
    {
      "timestamp": "2026-01-08T23:25:44.588Z",
      "block": 24193222,
      "rpcCalls": 6,
      "dataChanged": true,
      "errors": []
    },
    {
      "timestamp": "2026-01-08T23:27:46.883Z",
      "block": 24193232,
      "rpcCalls": 6,
      "dataChanged": true,
      "errors": []
    },
    {
      "timestamp": "2026-01-08T23:30:48.095Z",
      "block": 24193247,
      "rpcCalls": 6,
      "dataChanged": true,
      "errors": []
    },
    {
      "timestamp": "2026-01-08T23:35:38.965Z",
      "block": 24193271,
      "rpcCalls": 6,
      "dataChanged": true,
      "errors": []
    },
    {
      "timestamp": "2026-01-08T23:40:38.071Z",
      "block": 24193296,
      "rpcCalls": 6,
      "dataChanged": true,
      "errors": []
    },
    {
      "timestamp": "2026-01-08T23:45:43.239Z",
      "block": 24193322,
      "rpcCalls": 6,
      "dataChanged": true,
      "errors": []
    },
    {
      "timestamp": "2026-01-08T23:50:42.048Z",
      "block": 24193347,
      "rpcCalls": 6,
      "dataChanged": true,
      "errors": []
    },
    {
      "timestamp": "2026-01-08T23:55:39.387Z",
      "block": 24193372,
      "rpcCalls": 6,
      "dataChanged": true,
      "errors": []
    },
    {
      "timestamp": "2026-01-09T00:00:40.225Z",
      "block": 24193396,
      "rpcCalls": 6,
      "dataChanged": true,
      "errors": []
    },
    {
      "timestamp": "2026-01-09T00:05:42.552Z",
      "block": 24193421,
      "rpcCalls": 6,
      "dataChanged": true,
      "errors": []
    },
    {
      "timestamp": "2026-01-09T00:10:40.284Z",
      "block": 24193446,
      "rpcCalls": 6,
      "dataChanged": true,
      "errors": []
    },
    {
      "timestamp": "2026-01-09T00:15:43.881Z",
      "block": 24193471,
      "rpcCalls": 6,
      "dataChanged": true,
      "errors": []
    },
    {
      "timestamp": "2026-01-09T00:20:52.859Z",
      "block": 24193496,
      "rpcCalls": 6,
      "dataChanged": true,
      "errors": []
    },
    {
      "timestamp": "2026-01-09T00:23:04.857Z",
      "block": 24193508,
      "rpcCalls": 6,
      "dataChanged": true,
      "errors": []
    },
    {
      "timestamp": "2026-01-09T00:25:40.767Z",
      "block": 24193521,
      "rpcCalls": 6,
      "dataChanged": true,
      "errors": []
    },
    {
      "timestamp": "2026-01-09T00:30:39.738Z",
      "block": 24193546,
      "rpcCalls": 6,
      "dataChanged": true,
      "errors": []
    },
    {
      "timestamp": "2026-01-09T00:35:41.340Z",
      "block": 24193571,
      "rpcCalls": 6,
      "dataChanged": true,
      "errors": []
    },
    {
      "timestamp": "2026-01-09T00:40:39.907Z",
      "block": 24193595,
      "rpcCalls": 6,
      "dataChanged": true,
      "errors": []
    },
    {
      "timestamp": "2026-01-09T00:45:42.253Z",
      "block": 24193620,
      "rpcCalls": 6,
      "dataChanged": true,
      "errors": []
    },
    {
      "timestamp": "2026-01-09T00:50:47.665Z",
      "block": 24193646,
      "rpcCalls": 6,
      "dataChanged": true,
      "errors": []
    },
    {
      "timestamp": "2026-01-09T00:55:49.370Z",
      "block": 24193671,
      "rpcCalls": 6,
      "dataChanged": true,
      "errors": []
    },
    {
      "timestamp": "2026-01-09T01:00:55.110Z",
      "block": 24193696,
      "rpcCalls": 6,
      "dataChanged": true,
      "errors": []
    },
    {
      "timestamp": "2026-01-09T01:05:44.364Z",
      "block": 24193720,
      "rpcCalls": 6,
      "dataChanged": true,
      "errors": []
    },
    {
      "timestamp": "2026-01-09T01:10:41.079Z",
      "block": 24193745,
      "rpcCalls": 6,
      "dataChanged": true,
      "errors": []
    },
    {
      "timestamp": "2026-01-09T01:15:39.427Z",
      "block": 24193770,
      "rpcCalls": 6,
      "dataChanged": true,
      "errors": []
    },
    {
      "timestamp": "2026-01-09T01:18:22.533Z",
      "block": 24193783,
      "rpcCalls": 6,
      "dataChanged": true,
      "errors": []
    },
    {
      "timestamp": "2026-01-09T01:20:40.896Z",
      "block": 24193794,
      "rpcCalls": 6,
      "dataChanged": true,
      "errors": []
    },
    {
      "timestamp": "2026-01-09T01:25:41.390Z",
      "block": 24193819,
      "rpcCalls": 6,
      "dataChanged": true,
      "errors": []
    },
    {
      "timestamp": "2026-01-09T01:30:37.648Z",
      "block": 24193843,
      "rpcCalls": 6,
      "dataChanged": true,
      "errors": []
    },
    {
      "timestamp": "2026-01-09T01:35:38.833Z",
      "block": 24193868,
      "rpcCalls": 6,
      "dataChanged": true,
      "errors": []
    },
    {
      "timestamp": "2026-01-09T01:40:46.567Z",
      "block": 24193893,
      "rpcCalls": 6,
      "dataChanged": true,
      "errors": []
    },
    {
      "timestamp": "2026-01-09T01:46:13.135Z",
      "block": 24193921,
      "rpcCalls": 6,
      "dataChanged": true,
      "errors": []
    },
    {
      "timestamp": "2026-01-09T01:50:41.830Z",
      "block": 24193943,
      "rpcCalls": 6,
      "dataChanged": true,
      "errors": []
    },
    {
      "timestamp": "2026-01-09T01:55:42.101Z",
      "block": 24193968,
      "rpcCalls": 6,
      "dataChanged": true,
      "errors": []
    },
    {
      "timestamp": "2026-01-09T02:00:40.885Z",
      "block": 24193993,
      "rpcCalls": 6,
      "dataChanged": true,
      "errors": []
    },
    {
      "timestamp": "2026-01-09T02:05:43.179Z",
      "block": 24194019,
      "rpcCalls": 6,
      "dataChanged": true,
      "errors": []
    },
    {
      "timestamp": "2026-01-09T02:10:42.057Z",
      "block": 24194043,
      "rpcCalls": 6,
      "dataChanged": true,
      "errors": []
    },
    {
      "timestamp": "2026-01-09T02:13:50.761Z",
      "block": 24194059,
      "rpcCalls": 6,
      "dataChanged": true,
      "errors": []
    },
    {
      "timestamp": "2026-01-09T02:15:43.687Z",
      "block": 24194069,
      "rpcCalls": 6,
      "dataChanged": true,
      "errors": []
    },
    {
      "timestamp": "2026-01-09T02:20:43.848Z",
      "block": 24194094,
      "rpcCalls": 6,
      "dataChanged": true,
      "errors": []
    },
    {
      "timestamp": "2026-01-09T02:25:44.092Z",
      "block": 24194118,
      "rpcCalls": 6,
      "dataChanged": true,
      "errors": []
    },
    {
      "timestamp": "2026-01-09T02:30:43.922Z",
      "block": 24194144,
      "rpcCalls": 6,
      "dataChanged": true,
      "errors": []
    },
    {
      "timestamp": "2026-01-09T02:35:46.333Z",
      "block": 24194168,
      "rpcCalls": 6,
      "dataChanged": true,
      "errors": []
    },
    {
      "timestamp": "2026-01-09T02:40:44.350Z",
      "block": 24194193,
      "rpcCalls": 6,
      "dataChanged": true,
      "errors": []
    },
    {
      "timestamp": "2026-01-09T02:41:32.417Z",
      "block": 24194198,
      "rpcCalls": 6,
      "dataChanged": true,
      "errors": []
    },
    {
      "timestamp": "2026-01-09T02:45:41.252Z",
      "block": 24194218,
      "rpcCalls": 6,
      "dataChanged": true,
      "errors": []
    },
    {
      "timestamp": "2026-01-09T02:50:41.463Z",
      "block": 24194242,
      "rpcCalls": 6,
      "dataChanged": true,
      "errors": []
    },
    {
      "timestamp": "2026-01-09T02:55:42.209Z",
      "block": 24194266,
      "rpcCalls": 6,
      "dataChanged": true,
      "errors": []
    },
    {
      "timestamp": "2026-01-09T03:00:42.577Z",
      "block": 24194291,
      "rpcCalls": 6,
      "dataChanged": true,
      "errors": []
    },
    {
      "timestamp": "2026-01-09T03:05:40.864Z",
      "block": 24194316,
      "rpcCalls": 6,
      "dataChanged": true,
      "errors": []
    },
    {
      "timestamp": "2026-01-09T03:09:12.884Z",
      "block": 24194334,
      "rpcCalls": 6,
      "dataChanged": true,
      "errors": []
    },
    {
      "timestamp": "2026-01-09T03:10:39.990Z",
      "block": 24194341,
      "rpcCalls": 6,
      "dataChanged": true,
      "errors": []
    },
    {
      "timestamp": "2026-01-09T03:15:43.331Z",
      "block": 24194366,
      "rpcCalls": 6,
      "dataChanged": true,
      "errors": []
    },
    {
      "timestamp": "2026-01-09T03:20:44.190Z",
      "block": 24194392,
      "rpcCalls": 6,
      "dataChanged": true,
      "errors": []
    },
    {
      "timestamp": "2026-01-09T03:25:42.663Z",
      "block": 24194415,
      "rpcCalls": 6,
      "dataChanged": true,
      "errors": []
    },
    {
      "timestamp": "2026-01-09T03:30:43.873Z",
      "block": 24194441,
      "rpcCalls": 6,
      "dataChanged": true,
      "errors": []
    },
    {
      "timestamp": "2026-01-09T03:35:44.740Z",
      "block": 24194465,
      "rpcCalls": 6,
      "dataChanged": true,
      "errors": []
    },
    {
      "timestamp": "2026-01-09T03:36:54.310Z",
      "block": 24194471,
      "rpcCalls": 6,
      "dataChanged": true,
      "errors": []
    },
    {
      "timestamp": "2026-01-09T03:40:42.832Z",
      "block": 24194491,
      "rpcCalls": 6,
      "dataChanged": true,
      "errors": []
    },
    {
      "timestamp": "2026-01-09T03:45:44.478Z",
      "block": 24194516,
      "rpcCalls": 6,
      "dataChanged": true,
      "errors": []
    },
    {
      "timestamp": "2026-01-09T03:50:40.812Z",
      "block": 24194540,
      "rpcCalls": 6,
      "dataChanged": true,
      "errors": []
    },
    {
      "timestamp": "2026-01-09T03:55:41.916Z",
      "block": 24194565,
      "rpcCalls": 6,
      "dataChanged": true,
      "errors": []
    },
    {
      "timestamp": "2026-01-09T04:01:00.257Z",
      "block": 24194590,
      "rpcCalls": 6,
      "dataChanged": true,
      "errors": []
    },
    {
      "timestamp": "2026-01-09T04:04:54.881Z",
      "block": 24194610,
      "rpcCalls": 6,
      "dataChanged": true,
      "errors": []
    },
    {
      "timestamp": "2026-01-09T04:05:57.080Z",
      "block": 24194615,
      "rpcCalls": 6,
      "dataChanged": true,
      "errors": []
    },
    {
      "timestamp": "2026-01-09T04:10:59.000Z",
      "block": 24194640,
      "rpcCalls": 6,
      "dataChanged": true,
      "errors": []
    },
    {
      "timestamp": "2026-01-09T04:15:59.084Z",
      "block": 24194665,
      "rpcCalls": 6,
      "dataChanged": true,
      "errors": []
    },
    {
      "timestamp": "2026-01-09T04:20:58.557Z",
      "block": 24194691,
      "rpcCalls": 6,
      "dataChanged": true,
      "errors": []
    },
    {
      "timestamp": "2026-01-09T04:25:55.932Z",
      "block": 24194716,
      "rpcCalls": 6,
      "dataChanged": true,
      "errors": []
    },
    {
      "timestamp": "2026-01-09T04:30:56.396Z",
      "block": 24194741,
      "rpcCalls": 6,
      "dataChanged": true,
      "errors": []
    },
    {
      "timestamp": "2026-01-09T04:32:33.608Z",
      "block": 24194749,
      "rpcCalls": 6,
      "dataChanged": true,
      "errors": []
    },
    {
      "timestamp": "2026-01-09T04:35:56.238Z",
      "block": 24194766,
      "rpcCalls": 6,
      "dataChanged": true,
      "errors": []
    },
    {
      "timestamp": "2026-01-09T04:40:57.742Z",
      "block": 24194791,
      "rpcCalls": 6,
      "dataChanged": true,
      "errors": []
    },
    {
      "timestamp": "2026-01-09T04:45:55.610Z",
      "block": 24194815,
      "rpcCalls": 6,
      "dataChanged": true,
      "errors": []
    },
    {
      "timestamp": "2026-01-09T04:50:56.819Z",
      "block": 24194840,
      "rpcCalls": 6,
      "dataChanged": true,
      "errors": []
    },
    {
      "timestamp": "2026-01-09T04:55:56.409Z",
      "block": 24194865,
      "rpcCalls": 6,
      "dataChanged": true,
      "errors": []
    }
  ],
  "totalRpcCalls": 257203
}