{
  "lastBlockNumber": 22945395,
  "lastUpdateTime": 1752833407428,
  "totalRpcCalls": 315,
  "updates": [
    {
      "timestamp": "2025-07-16T15:25:14.631Z",
      "block": 22932631,
      "rpcCalls": 1,
      "dataChanged": true,
      "errors": []
    },
    {
      "timestamp": "2025-07-16T15:45:30.217Z",
      "block": 22932733,
      "rpcCalls": 1,
      "dataChanged": true,
      "errors": []
    },
    {
      "timestamp": "2025-07-16T16:28:02.506Z",
      "block": 22932941,
      "rpcCalls": 1,
      "dataChanged": true,
      "errors": []
    },
    {
      "timestamp": "2025-07-16T17:08:30.804Z",
      "block": 22933144,
      "rpcCalls": 1,
      "dataChanged": true,
      "errors": []
    },
    {
      "timestamp": "2025-07-16T17:26:46.449Z",
      "block": 22933235,
      "rpcCalls": 11,
      "dataChanged": true,
      "errors": []
    },
    {
      "timestamp": "2025-07-16T18:38:13.605Z",
      "block": 22933592,
      "rpcCalls": 3,
      "dataChanged": true,
      "errors": []
    },
    {
      "timestamp": "2025-07-16T18:51:01.316Z",
      "block": 22933656,
      "rpcCalls": 3,
      "dataChanged": true,
      "errors": []
    },
    {
      "timestamp": "2025-07-16T19:54:28.322Z",
      "block": 22933972,
      "rpcCalls": 3,
      "dataChanged": true,
      "errors": []
    },
    {
      "timestamp": "2025-07-16T22:40:49.429Z",
      "block": 22934799,
      "rpcCalls": 3,
      "dataChanged": true,
      "errors": []
    },
    {
      "timestamp": "2025-07-16T22:45:04.235Z",
      "block": 22934821,
      "rpcCalls": 3,
      "dataChanged": true,
      "errors": []
    },
    {
      "timestamp": "2025-07-16T23:04:52.532Z",
      "block": 22934920,
      "rpcCalls": 3,
      "dataChanged": true,
      "errors": []
    },
    {
      "timestamp": "2025-07-16T23:12:11.922Z",
      "block": 22934955,
      "rpcCalls": 3,
      "dataChanged": true,
      "errors": []
    },
    {
      "timestamp": "2025-07-16T23:56:56.039Z",
      "block": 22935176,
      "rpcCalls": 3,
      "dataChanged": true,
      "errors": []
    },
    {
      "timestamp": "2025-07-17T17:00:07.553Z",
      "block": 22940276,
      "rpcCalls": 3,
      "dataChanged": true,
      "errors": []
    },
    {
      "timestamp": "2025-07-17T17:30:06.589Z",
      "block": 22940426,
      "rpcCalls": 3,
      "dataChanged": true,
      "errors": []
    },
    {
      "timestamp": "2025-07-17T17:57:24.984Z",
      "block": 22940562,
      "rpcCalls": 4,
      "dataChanged": true,
      "errors": []
    },
    {
      "timestamp": "2025-07-17T18:00:06.559Z",
      "block": 22940576,
      "rpcCalls": 4,
      "dataChanged": true,
      "errors": []
    },
    {
      "timestamp": "2025-07-17T18:07:50.671Z",
      "block": 22940614,
      "rpcCalls": 4,
      "dataChanged": true,
      "errors": []
    },
    {
      "timestamp": "2025-07-17T18:11:03.609Z",
      "block": 22940630,
      "rpcCalls": 4,
      "dataChanged": true,
      "errors": []
    },
    {
      "timestamp": "2025-07-17T18:17:17.277Z",
      "block": 22940661,
      "rpcCalls": 4,
      "dataChanged": true,
      "errors": []
    },
    {
      "timestamp": "2025-07-17T18:19:38.434Z",
      "block": 22940673,
      "rpcCalls": 4,
      "dataChanged": true,
      "errors": []
    },
    {
      "timestamp": "2025-07-17T18:30:06.902Z",
      "block": 22940726,
      "rpcCalls": 4,
      "dataChanged": true,
      "errors": []
    },
    {
      "timestamp": "2025-07-17T18:34:54.058Z",
      "block": 22940750,
      "rpcCalls": 4,
      "dataChanged": true,
      "errors": []
    },
    {
      "timestamp": "2025-07-17T19:00:07.004Z",
      "block": 22940876,
      "rpcCalls": 4,
      "dataChanged": true,
      "errors": []
    },
    {
      "timestamp": "2025-07-17T19:30:07.134Z",
      "block": 22941026,
      "rpcCalls": 4,
      "dataChanged": true,
      "errors": []
    },
    {
      "timestamp": "2025-07-17T20:00:06.794Z",
      "block": 22941174,
      "rpcCalls": 4,
      "dataChanged": true,
      "errors": []
    },
    {
      "timestamp": "2025-07-17T20:30:06.520Z",
      "block": 22941325,
      "rpcCalls": 4,
      "dataChanged": true,
      "errors": []
    },
    {
      "timestamp": "2025-07-17T21:00:06.405Z",
      "block": 22941473,
      "rpcCalls": 4,
      "dataChanged": true,
      "errors": []
    },
    {
      "timestamp": "2025-07-17T21:30:07.828Z",
      "block": 22941620,
      "rpcCalls": 4,
      "dataChanged": true,
      "errors": []
    },
    {
      "timestamp": "2025-07-17T22:00:07.382Z",
      "block": 22941769,
      "rpcCalls": 4,
      "dataChanged": true,
      "errors": []
    },
    {
      "timestamp": "2025-07-17T22:30:06.954Z",
      "block": 22941918,
      "rpcCalls": 4,
      "dataChanged": true,
      "errors": []
    },
    {
      "timestamp": "2025-07-17T23:00:07.532Z",
      "block": 22942067,
      "rpcCalls": 4,
      "dataChanged": true,
      "errors": []
    },
    {
      "timestamp": "2025-07-17T23:30:07.821Z",
      "block": 22942217,
      "rpcCalls": 4,
      "dataChanged": true,
      "errors": []
    },
    {
      "timestamp": "2025-07-18T00:00:07.065Z",
      "block": 22942366,
      "rpcCalls": 4,
      "dataChanged": true,
      "errors": []
    },
    {
      "timestamp": "2025-07-18T00:30:07.701Z",
      "block": 22942515,
      "rpcCalls": 4,
      "dataChanged": true,
      "errors": []
    },
    {
      "timestamp": "2025-07-18T01:00:07.374Z",
      "block": 22942663,
      "rpcCalls": 4,
      "dataChanged": true,
      "errors": []
    },
    {
      "timestamp": "2025-07-18T01:30:07.454Z",
      "block": 22942814,
      "rpcCalls": 4,
      "dataChanged": true,
      "errors": []
    },
    {
      "timestamp": "2025-07-18T02:00:06.892Z",
      "block": 22942961,
      "rpcCalls": 4,
      "dataChanged": true,
      "errors": []
    },
    {
      "timestamp": "2025-07-18T02:30:07.252Z",
      "block": 22943111,
      "rpcCalls": 4,
      "dataChanged": true,
      "errors": []
    },
    {
      "timestamp": "2025-07-18T03:00:08.382Z",
      "block": 22943259,
      "rpcCalls": 4,
      "dataChanged": true,
      "errors": []
    },
    {
      "timestamp": "2025-07-18T03:30:07.126Z",
      "block": 22943407,
      "rpcCalls": 4,
      "dataChanged": true,
      "errors": []
    },
    {
      "timestamp": "2025-07-18T03:40:06.566Z",
      "block": 22943457,
      "rpcCalls": 4,
      "dataChanged": true,
      "errors": []
    },
    {
      "timestamp": "2025-07-18T03:50:06.657Z",
      "block": 22943508,
      "rpcCalls": 4,
      "dataChanged": true,
      "errors": []
    },
    {
      "timestamp": "2025-07-18T04:00:06.424Z",
      "block": 22943557,
      "rpcCalls": 4,
      "dataChanged": true,
      "errors": []
    },
    {
      "timestamp": "2025-07-18T04:10:06.456Z",
      "block": 22943607,
      "rpcCalls": 4,
      "dataChanged": true,
      "errors": []
    },
    {
      "timestamp": "2025-07-18T04:20:06.883Z",
      "block": 22943656,
      "rpcCalls": 4,
      "dataChanged": true,
      "errors": []
    },
    {
      "timestamp": "2025-07-18T04:30:07.439Z",
      "block": 22943707,
      "rpcCalls": 4,
      "dataChanged": true,
      "errors": []
    },
    {
      "timestamp": "2025-07-18T04:32:21.400Z",
      "block": 22943718,
      "rpcCalls": 4,
      "dataChanged": true,
      "errors": []
    },
    {
      "timestamp": "2025-07-18T04:40:06.973Z",
      "block": 22943755,
      "rpcCalls": 4,
      "dataChanged": true,
      "errors": []
    },
    {
      "timestamp": "2025-07-18T04:50:06.743Z",
      "block": 22943806,
      "rpcCalls": 4,
      "dataChanged": true,
      "errors": []
    },
    {
      "timestamp": "2025-07-18T05:00:07.734Z",
      "block": 22943856,
      "rpcCalls": 4,
      "dataChanged": true,
      "errors": []
    },
    {
      "timestamp": "2025-07-18T05:03:44.036Z",
      "block": 22943874,
      "rpcCalls": 4,
      "dataChanged": true,
      "errors": []
    },
    {
      "timestamp": "2025-07-18T05:10:07.069Z",
      "block": 22943905,
      "rpcCalls": 4,
      "dataChanged": true,
      "errors": []
    },
    {
      "timestamp": "2025-07-18T05:20:06.153Z",
      "block": 22943954,
      "rpcCalls": 4,
      "dataChanged": true,
      "errors": []
    },
    {
      "timestamp": "2025-07-18T05:30:06.034Z",
      "block": 22944004,
      "rpcCalls": 4,
      "dataChanged": true,
      "errors": []
    },
    {
      "timestamp": "2025-07-18T05:40:06.113Z",
      "block": 22944054,
      "rpcCalls": 4,
      "dataChanged": true,
      "errors": []
    },
    {
      "timestamp": "2025-07-18T05:50:05.840Z",
      "block": 22944102,
      "rpcCalls": 4,
      "dataChanged": true,
      "errors": []
    },
    {
      "timestamp": "2025-07-18T06:00:07.292Z",
      "block": 22944152,
      "rpcCalls": 4,
      "dataChanged": true,
      "errors": []
    },
    {
      "timestamp": "2025-07-18T06:10:06.536Z",
      "block": 22944201,
      "rpcCalls": 4,
      "dataChanged": true,
      "errors": []
    },
    {
      "timestamp": "2025-07-18T06:20:06.685Z",
      "block": 22944251,
      "rpcCalls": 4,
      "dataChanged": true,
      "errors": []
    },
    {
      "timestamp": "2025-07-18T06:30:06.714Z",
      "block": 22944301,
      "rpcCalls": 4,
      "dataChanged": true,
      "errors": []
    },
    {
      "timestamp": "2025-07-18T06:40:06.625Z",
      "block": 22944351,
      "rpcCalls": 4,
      "dataChanged": true,
      "errors": []
    },
    {
      "timestamp": "2025-07-18T06:50:07.096Z",
      "block": 22944400,
      "rpcCalls": 4,
      "dataChanged": true,
      "errors": []
    },
    {
      "timestamp": "2025-07-18T07:00:06.522Z",
      "block": 22944450,
      "rpcCalls": 4,
      "dataChanged": true,
      "errors": []
    },
    {
      "timestamp": "2025-07-18T07:10:07.493Z",
      "block": 22944500,
      "rpcCalls": 4,
      "dataChanged": true,
      "errors": []
    },
    {
      "timestamp": "2025-07-18T07:20:07.028Z",
      "block": 22944550,
      "rpcCalls": 4,
      "dataChanged": true,
      "errors": []
    },
    {
      "timestamp": "2025-07-18T07:30:05.962Z",
      "block": 22944600,
      "rpcCalls": 2,
      "dataChanged": true,
      "errors": []
    },
    {
      "timestamp": "2025-07-18T07:40:07.350Z",
      "block": 22944650,
      "rpcCalls": 4,
      "dataChanged": true,
      "errors": []
    },
    {
      "timestamp": "2025-07-18T07:50:06.996Z",
      "block": 22944699,
      "rpcCalls": 4,
      "dataChanged": true,
      "errors": []
    },
    {
      "timestamp": "2025-07-18T08:00:06.993Z",
      "block": 22944749,
      "rpcCalls": 4,
      "dataChanged": true,
      "errors": []
    },
    {
      "timestamp": "2025-07-18T08:10:06.277Z",
      "block": 22944799,
      "rpcCalls": 4,
      "dataChanged": true,
      "errors": []
    },
    {
      "timestamp": "2025-07-18T08:20:07.075Z",
      "block": 22944849,
      "rpcCalls": 4,
      "dataChanged": true,
      "errors": []
    },
    {
      "timestamp": "2025-07-18T08:30:07.158Z",
      "block": 22944899,
      "rpcCalls": 4,
      "dataChanged": true,
      "errors": []
    },
    {
      "timestamp": "2025-07-18T08:40:06.592Z",
      "block": 22944948,
      "rpcCalls": 4,
      "dataChanged": true,
      "errors": []
    },
    {
      "timestamp": "2025-07-18T08:50:07.003Z",
      "block": 22944998,
      "rpcCalls": 4,
      "dataChanged": true,
      "errors": []
    },
    {
      "timestamp": "2025-07-18T09:00:06.927Z",
      "block": 22945048,
      "rpcCalls": 4,
      "dataChanged": true,
      "errors": []
    },
    {
      "timestamp": "2025-07-18T09:10:07.112Z",
      "block": 22945098,
      "rpcCalls": 4,
      "dataChanged": true,
      "errors": []
    },
    {
      "timestamp": "2025-07-18T09:20:05.963Z",
      "block": 22945146,
      "rpcCalls": 4,
      "dataChanged": true,
      "errors": []
    },
    {
      "timestamp": "2025-07-18T09:30:06.971Z",
      "block": 22945197,
      "rpcCalls": 4,
      "dataChanged": true,
      "errors": []
    },
    {
      "timestamp": "2025-07-18T09:40:08.065Z",
      "block": 22945247,
      "rpcCalls": 4,
      "dataChanged": true,
      "errors": []
    },
    {
      "timestamp": "2025-07-18T09:50:05.903Z",
      "block": 22945297,
      "rpcCalls": 4,
      "dataChanged": true,
      "errors": []
    },
    {
      "timestamp": "2025-07-18T10:00:06.869Z",
      "block": 22945346,
      "rpcCalls": 4,
      "dataChanged": true,
      "errors": []
    },
    {
      "timestamp": "2025-07-18T10:10:07.429Z",
      "block": 22945395,
      "rpcCalls": 4,
      "dataChanged": true,
      "errors": []
    }
  ]
}