{
  "startTime": 1754170500998,
  "rpcCalls": 0,
  "lastBlockNumber": 23491626,
  "lastUpdateTime": 1759426674439,
  "updateHistory": [
    {
      "timestamp": "2025-10-02T09:48:17.155Z",
      "block": 23489289,
      "rpcCalls": 6,
      "dataChanged": true,
      "errors": []
    },
    {
      "timestamp": "2025-10-02T09:52:17.743Z",
      "block": 23489314,
      "rpcCalls": 6,
      "dataChanged": true,
      "errors": []
    },
    {
      "timestamp": "2025-10-02T09:54:56.626Z",
      "block": 23489327,
      "rpcCalls": 6,
      "dataChanged": true,
      "errors": []
    },
    {
      "timestamp": "2025-10-02T09:57:14.882Z",
      "block": 23489338,
      "rpcCalls": 6,
      "dataChanged": true,
      "errors": []
    },
    {
      "timestamp": "2025-10-02T10:02:20.157Z",
      "block": 23489363,
      "rpcCalls": 6,
      "dataChanged": true,
      "errors": []
    },
    {
      "timestamp": "2025-10-02T10:07:17.140Z",
      "block": 23489388,
      "rpcCalls": 6,
      "dataChanged": true,
      "errors": []
    },
    {
      "timestamp": "2025-10-02T10:14:30.933Z",
      "block": 23489413,
      "rpcCalls": 6,
      "dataChanged": true,
      "errors": []
    },
    {
      "timestamp": "2025-10-02T10:17:15.507Z",
      "block": 23489436,
      "rpcCalls": 6,
      "dataChanged": true,
      "errors": []
    },
    {
      "timestamp": "2025-10-02T10:22:19.589Z",
      "block": 23489461,
      "rpcCalls": 6,
      "dataChanged": true,
      "errors": []
    },
    {
      "timestamp": "2025-10-02T10:24:57.972Z",
      "block": 23489474,
      "rpcCalls": 6,
      "dataChanged": true,
      "errors": []
    },
    {
      "timestamp": "2025-10-02T10:27:13.523Z",
      "block": 23489486,
      "rpcCalls": 6,
      "dataChanged": true,
      "errors": []
    },
    {
      "timestamp": "2025-10-02T10:32:17.691Z",
      "block": 23489510,
      "rpcCalls": 6,
      "dataChanged": true,
      "errors": []
    },
    {
      "timestamp": "2025-10-02T10:37:19.562Z",
      "block": 23489535,
      "rpcCalls": 6,
      "dataChanged": true,
      "errors": []
    },
    {
      "timestamp": "2025-10-02T10:42:23.156Z",
      "block": 23489559,
      "rpcCalls": 6,
      "dataChanged": true,
      "errors": []
    },
    {
      "timestamp": "2025-10-02T10:47:18.456Z",
      "block": 23489585,
      "rpcCalls": 6,
      "dataChanged": true,
      "errors": []
    },
    {
      "timestamp": "2025-10-02T10:52:17.891Z",
      "block": 23489610,
      "rpcCalls": 6,
      "dataChanged": true,
      "errors": []
    },
    {
      "timestamp": "2025-10-02T10:55:00.632Z",
      "block": 23489623,
      "rpcCalls": 6,
      "dataChanged": true,
      "errors": []
    },
    {
      "timestamp": "2025-10-02T10:57:16.685Z",
      "block": 23489635,
      "rpcCalls": 6,
      "dataChanged": true,
      "errors": []
    },
    {
      "timestamp": "2025-10-02T11:02:16.501Z",
      "block": 23489660,
      "rpcCalls": 6,
      "dataChanged": true,
      "errors": []
    },
    {
      "timestamp": "2025-10-02T11:07:17.344Z",
      "block": 23489684,
      "rpcCalls": 6,
      "dataChanged": true,
      "errors": []
    },
    {
      "timestamp": "2025-10-02T11:12:14.863Z",
      "block": 23489709,
      "rpcCalls": 6,
      "dataChanged": true,
      "errors": []
    },
    {
      "timestamp": "2025-10-02T11:17:17.546Z",
      "block": 23489734,
      "rpcCalls": 6,
      "dataChanged": true,
      "errors": []
    },
    {
      "timestamp": "2025-10-02T11:22:18.517Z",
      "block": 23489759,
      "rpcCalls": 6,
      "dataChanged": true,
      "errors": []
    },
    {
      "timestamp": "2025-10-02T11:25:00.214Z",
      "block": 23489772,
      "rpcCalls": 6,
      "dataChanged": true,
      "errors": []
    },
    {
      "timestamp": "2025-10-02T11:27:17.523Z",
      "block": 23489784,
      "rpcCalls": 6,
      "dataChanged": true,
      "errors": []
    },
    {
      "timestamp": "2025-10-02T11:32:16.333Z",
      "block": 23489809,
      "rpcCalls": 6,
      "dataChanged": true,
      "errors": []
    },
    {
      "timestamp": "2025-10-02T11:37:19.892Z",
      "block": 23489834,
      "rpcCalls": 6,
      "dataChanged": true,
      "errors": []
    },
    {
      "timestamp": "2025-10-02T11:42:16.080Z",
      "block": 23489859,
      "rpcCalls": 6,
      "dataChanged": true,
      "errors": []
    },
    {
      "timestamp": "2025-10-02T11:47:18.727Z",
      "block": 23489883,
      "rpcCalls": 6,
      "dataChanged": true,
      "errors": []
    },
    {
      "timestamp": "2025-10-02T11:52:19.467Z",
      "block": 23489907,
      "rpcCalls": 6,
      "dataChanged": true,
      "errors": []
    },
    {
      "timestamp": "2025-10-02T11:54:59.626Z",
      "block": 23489921,
      "rpcCalls": 6,
      "dataChanged": true,
      "errors": []
    },
    {
      "timestamp": "2025-10-02T11:57:15.594Z",
      "block": 23489933,
      "rpcCalls": 6,
      "dataChanged": true,
      "errors": []
    },
    {
      "timestamp": "2025-10-02T12:02:25.704Z",
      "block": 23489958,
      "rpcCalls": 6,
      "dataChanged": true,
      "errors": []
    },
    {
      "timestamp": "2025-10-02T12:07:31.320Z",
      "block": 23489983,
      "rpcCalls": 6,
      "dataChanged": true,
      "errors": []
    },
    {
      "timestamp": "2025-10-02T12:12:27.523Z",
      "block": 23490008,
      "rpcCalls": 6,
      "dataChanged": true,
      "errors": []
    },
    {
      "timestamp": "2025-10-02T12:17:27.993Z",
      "block": 23490033,
      "rpcCalls": 6,
      "dataChanged": true,
      "errors": []
    },
    {
      "timestamp": "2025-10-02T12:22:28.500Z",
      "block": 23490056,
      "rpcCalls": 6,
      "dataChanged": true,
      "errors": []
    },
    {
      "timestamp": "2025-10-02T12:27:21.471Z",
      "block": 23490081,
      "rpcCalls": 6,
      "dataChanged": true,
      "errors": []
    },
    {
      "timestamp": "2025-10-02T12:32:28.949Z",
      "block": 23490107,
      "rpcCalls": 6,
      "dataChanged": true,
      "errors": []
    },
    {
      "timestamp": "2025-10-02T12:37:31.854Z",
      "block": 23490131,
      "rpcCalls": 6,
      "dataChanged": true,
      "errors": []
    },
    {
      "timestamp": "2025-10-02T12:42:31.190Z",
      "block": 23490157,
      "rpcCalls": 6,
      "dataChanged": true,
      "errors": []
    },
    {
      "timestamp": "2025-10-02T12:47:40.961Z",
      "block": 23490181,
      "rpcCalls": 6,
      "dataChanged": true,
      "errors": []
    },
    {
      "timestamp": "2025-10-02T12:52:33.428Z",
      "block": 23490206,
      "rpcCalls": 6,
      "dataChanged": true,
      "errors": []
    },
    {
      "timestamp": "2025-10-02T12:57:30.344Z",
      "block": 23490231,
      "rpcCalls": 6,
      "dataChanged": true,
      "errors": []
    },
    {
      "timestamp": "2025-10-02T13:02:28.930Z",
      "block": 23490257,
      "rpcCalls": 6,
      "dataChanged": true,
      "errors": []
    },
    {
      "timestamp": "2025-10-02T13:07:44.069Z",
      "block": 23490282,
      "rpcCalls": 6,
      "dataChanged": true,
      "errors": [
        "Buy & Process update: Command failed: node scripts/update-buy-process-data.js"
      ]
    },
    {
      "timestamp": "2025-10-02T13:12:34.809Z",
      "block": 23490307,
      "rpcCalls": 6,
      "dataChanged": true,
      "errors": []
    },
    {
      "timestamp": "2025-10-02T13:17:36.591Z",
      "block": 23490331,
      "rpcCalls": 6,
      "dataChanged": true,
      "errors": []
    },
    {
      "timestamp": "2025-10-02T13:22:31.850Z",
      "block": 23490357,
      "rpcCalls": 6,
      "dataChanged": true,
      "errors": []
    },
    {
      "timestamp": "2025-10-02T13:27:27.343Z",
      "block": 23490382,
      "rpcCalls": 6,
      "dataChanged": true,
      "errors": []
    },
    {
      "timestamp": "2025-10-02T13:32:25.736Z",
      "block": 23490407,
      "rpcCalls": 6,
      "dataChanged": true,
      "errors": []
    },
    {
      "timestamp": "2025-10-02T13:37:27.964Z",
      "block": 23490432,
      "rpcCalls": 6,
      "dataChanged": true,
      "errors": []
    },
    {
      "timestamp": "2025-10-02T13:42:32.788Z",
      "block": 23490456,
      "rpcCalls": 7,
      "dataChanged": true,
      "errors": []
    },
    {
      "timestamp": "2025-10-02T13:47:32.046Z",
      "block": 23490481,
      "rpcCalls": 6,
      "dataChanged": true,
      "errors": []
    },
    {
      "timestamp": "2025-10-02T13:52:37.640Z",
      "block": 23490506,
      "rpcCalls": 6,
      "dataChanged": true,
      "errors": []
    },
    {
      "timestamp": "2025-10-02T13:57:31.460Z",
      "block": 23490531,
      "rpcCalls": 5,
      "dataChanged": true,
      "errors": [
        "Pool update: missing revert data in call exception; Transaction reverted without a reason string [ See: https://links.ethers.org/v5-errors-CALL_EXCEPTION ] (data=\"0x\", transaction={\"to\":\"0x7ff1f30F6E7EeC2ff3F0D1b60739115BDF88190F\",\"data\":\"0x3850c7bd\",\"accessList\":null}, error={\"reason\":\"bad response\",\"code\":\"SERVER_ERROR\",\"status\":408,\"headers\":{\"date\":\"Thu, 02 Oct 2025 13:55:04 GMT\",\"content-type\":\"application/json\",\"transfer-encoding\":\"chunked\",\"connection\":\"close\",\"cf-ray\":\"9884b1f63facf7a3-LAX\",\"access-control-allow-origin\":\"*\",\"vary\":\"Accept-Encoding\",\"x-drpc-owner-id\":\"cb501251-31a8-4028-8b0a-54679f15c385\",\"x-drpc-owner-tier\":\"free\",\"x-drpc-provider-id\":\"drpc-core-free\",\"x-drpc-trace-id\":\"04600c8aa727316288c22cae212ec23a\",\"strict-transport-security\":\"max-age=31536000; includeSubDomains\",\"access-control-allow-credentials\":\"true\",\"access-control-allow-methods\":\"GET, PUT, POST, DELETE, PATCH, OPTIONS\",\"access-control-allow-headers\":\"DNT,Keep-Alive,User-Agent,X-Requested-With,If-Modified-Since,Cache-Control,Content-Type,Range,Authorization\",\"access-control-max-age\":\"1728000\",\"cf-cache-status\":\"DYNAMIC\",\"server\":\"cloudflare\"},\"body\":\"{\\\"id\\\":48,\\\"jsonrpc\\\":\\\"2.0\\\",\\\"error\\\":{\\\"message\\\":\\\"Request timeout on the free tier, please upgrade your tier to the paid one\\\",\\\"code\\\":30}}\",\"requestBody\":\"{\\\"method\\\":\\\"eth_call\\\",\\\"params\\\":[{\\\"to\\\":\\\"0x7ff1f30f6e7eec2ff3f0d1b60739115bdf88190f\\\",\\\"data\\\":\\\"0x3850c7bd\\\"},\\\"latest\\\"],\\\"id\\\":48,\\\"jsonrpc\\\":\\\"2.0\\\"}\",\"requestMethod\":\"POST\",\"url\":\"https://eth.drpc.org\"}, code=CALL_EXCEPTION, version=providers/5.7.2)"
      ]
    },
    {
      "timestamp": "2025-10-02T14:02:36.030Z",
      "block": 23490556,
      "rpcCalls": 7,
      "dataChanged": true,
      "errors": []
    },
    {
      "timestamp": "2025-10-02T14:07:31.262Z",
      "block": 23490580,
      "rpcCalls": 6,
      "dataChanged": true,
      "errors": []
    },
    {
      "timestamp": "2025-10-02T14:12:27.640Z",
      "block": 23490606,
      "rpcCalls": 6,
      "dataChanged": true,
      "errors": []
    },
    {
      "timestamp": "2025-10-02T14:17:27.008Z",
      "block": 23490631,
      "rpcCalls": 6,
      "dataChanged": true,
      "errors": []
    },
    {
      "timestamp": "2025-10-02T14:22:28.547Z",
      "block": 23490655,
      "rpcCalls": 7,
      "dataChanged": true,
      "errors": []
    },
    {
      "timestamp": "2025-10-02T14:27:50.220Z",
      "block": 23490680,
      "rpcCalls": 6,
      "dataChanged": true,
      "errors": []
    },
    {
      "timestamp": "2025-10-02T14:33:23.726Z",
      "block": 23490701,
      "rpcCalls": 6,
      "dataChanged": true,
      "errors": []
    },
    {
      "timestamp": "2025-10-02T14:38:44.777Z",
      "block": 23490730,
      "rpcCalls": 6,
      "dataChanged": true,
      "errors": []
    },
    {
      "timestamp": "2025-10-02T14:43:45.188Z",
      "block": 23490756,
      "rpcCalls": 6,
      "dataChanged": true,
      "errors": []
    },
    {
      "timestamp": "2025-10-02T14:48:43.711Z",
      "block": 23490779,
      "rpcCalls": 6,
      "dataChanged": true,
      "errors": []
    },
    {
      "timestamp": "2025-10-02T14:53:47.274Z",
      "block": 23490804,
      "rpcCalls": 6,
      "dataChanged": true,
      "errors": []
    },
    {
      "timestamp": "2025-10-02T14:58:43.837Z",
      "block": 23490828,
      "rpcCalls": 6,
      "dataChanged": true,
      "errors": []
    },
    {
      "timestamp": "2025-10-02T15:03:38.481Z",
      "block": 23490853,
      "rpcCalls": 6,
      "dataChanged": true,
      "errors": []
    },
    {
      "timestamp": "2025-10-02T15:08:43.794Z",
      "block": 23490878,
      "rpcCalls": 6,
      "dataChanged": true,
      "errors": []
    },
    {
      "timestamp": "2025-10-02T15:13:36.624Z",
      "block": 23490902,
      "rpcCalls": 6,
      "dataChanged": true,
      "errors": []
    },
    {
      "timestamp": "2025-10-02T15:18:44.691Z",
      "block": 23490926,
      "rpcCalls": 6,
      "dataChanged": true,
      "errors": []
    },
    {
      "timestamp": "2025-10-02T15:23:47.730Z",
      "block": 23490951,
      "rpcCalls": 6,
      "dataChanged": true,
      "errors": []
    },
    {
      "timestamp": "2025-10-02T15:28:36.309Z",
      "block": 23490977,
      "rpcCalls": 6,
      "dataChanged": true,
      "errors": []
    },
    {
      "timestamp": "2025-10-02T15:33:49.459Z",
      "block": 23491001,
      "rpcCalls": 6,
      "dataChanged": true,
      "errors": []
    },
    {
      "timestamp": "2025-10-02T15:38:51.429Z",
      "block": 23491025,
      "rpcCalls": 6,
      "dataChanged": true,
      "errors": []
    },
    {
      "timestamp": "2025-10-02T15:43:42.260Z",
      "block": 23491050,
      "rpcCalls": 6,
      "dataChanged": true,
      "errors": []
    },
    {
      "timestamp": "2025-10-02T15:48:44.912Z",
      "block": 23491075,
      "rpcCalls": 6,
      "dataChanged": true,
      "errors": []
    },
    {
      "timestamp": "2025-10-02T15:53:39.947Z",
      "block": 23491101,
      "rpcCalls": 6,
      "dataChanged": true,
      "errors": []
    },
    {
      "timestamp": "2025-10-02T15:58:43.479Z",
      "block": 23491126,
      "rpcCalls": 6,
      "dataChanged": true,
      "errors": []
    },
    {
      "timestamp": "2025-10-02T16:03:44.024Z",
      "block": 23491151,
      "rpcCalls": 6,
      "dataChanged": true,
      "errors": []
    },
    {
      "timestamp": "2025-10-02T16:08:35.885Z",
      "block": 23491175,
      "rpcCalls": 6,
      "dataChanged": true,
      "errors": []
    },
    {
      "timestamp": "2025-10-02T16:13:45.484Z",
      "block": 23491200,
      "rpcCalls": 6,
      "dataChanged": true,
      "errors": []
    },
    {
      "timestamp": "2025-10-02T16:18:39.338Z",
      "block": 23491226,
      "rpcCalls": 6,
      "dataChanged": true,
      "errors": []
    },
    {
      "timestamp": "2025-10-02T16:24:07.623Z",
      "block": 23491256,
      "rpcCalls": 6,
      "dataChanged": true,
      "errors": []
    },
    {
      "timestamp": "2025-10-02T16:28:01.425Z",
      "block": 23491276,
      "rpcCalls": 6,
      "dataChanged": true,
      "errors": []
    },
    {
      "timestamp": "2025-10-02T16:32:56.291Z",
      "block": 23491300,
      "rpcCalls": 6,
      "dataChanged": true,
      "errors": []
    },
    {
      "timestamp": "2025-10-02T16:38:09.864Z",
      "block": 23491325,
      "rpcCalls": 6,
      "dataChanged": true,
      "errors": []
    },
    {
      "timestamp": "2025-10-02T16:43:04.576Z",
      "block": 23491350,
      "rpcCalls": 6,
      "dataChanged": true,
      "errors": []
    },
    {
      "timestamp": "2025-10-02T16:48:04.259Z",
      "block": 23491376,
      "rpcCalls": 6,
      "dataChanged": true,
      "errors": []
    },
    {
      "timestamp": "2025-10-02T16:53:42.510Z",
      "block": 23491403,
      "rpcCalls": 6,
      "dataChanged": true,
      "errors": []
    },
    {
      "timestamp": "2025-10-02T16:58:01.751Z",
      "block": 23491425,
      "rpcCalls": 6,
      "dataChanged": true,
      "errors": []
    },
    {
      "timestamp": "2025-10-02T17:03:14.111Z",
      "block": 23491451,
      "rpcCalls": 6,
      "dataChanged": true,
      "errors": []
    },
    {
      "timestamp": "2025-10-02T17:08:00.481Z",
      "block": 23491476,
      "rpcCalls": 6,
      "dataChanged": true,
      "errors": []
    },
    {
      "timestamp": "2025-10-02T17:12:54.941Z",
      "block": 23491501,
      "rpcCalls": 6,
      "dataChanged": true,
      "errors": []
    },
    {
      "timestamp": "2025-10-02T17:17:55.362Z",
      "block": 23491525,
      "rpcCalls": 6,
      "dataChanged": true,
      "errors": []
    },
    {
      "timestamp": "2025-10-02T17:22:48.668Z",
      "block": 23491551,
      "rpcCalls": 6,
      "dataChanged": true,
      "errors": []
    },
    {
      "timestamp": "2025-10-02T17:28:05.718Z",
      "block": 23491575,
      "rpcCalls": 6,
      "dataChanged": true,
      "errors": []
    },
    {
      "timestamp": "2025-10-02T17:33:03.542Z",
      "block": 23491601,
      "rpcCalls": 6,
      "dataChanged": true,
      "errors": []
    },
    {
      "timestamp": "2025-10-02T17:37:54.439Z",
      "block": 23491626,
      "rpcCalls": 6,
      "dataChanged": true,
      "errors": []
    }
  ],
  "totalRpcCalls": 105173
}